shell_piper/__init__.py
shell_piper/__main__.py
shell_piper/exe.py
shell_piper/file.py
shell_piper-0.7.2.dist-info/entry_points.txt
shell_piper-0.7.2.dist-info/LICENSE
shell_piper-0.7.2.dist-info/WHEEL
shell_piper-0.7.2.dist-info/METADATA
shell_piper-0.7.2.dist-info/RECORD
