Metadata-Version: 2.1
Name: shell-piper
Version: 0.7.2
Summary: Write a temporary file and pass it to a program
Author-email: Firegem <mrfiregem@protonmail.ch>
Requires-Python: >=3.9
Classifier: License :: OSI Approved :: GNU General Public License v3 or later (GPLv3+)
Classifier: Natural Language :: English
Classifier: Programming Language :: Python
Classifier: Programming Language :: Python :: 3.9
Requires-Dist: black>=22.12 ; extra == "dev"
Requires-Dist: flit ; extra == "dev"
Requires-Dist: mypy>=0.991 ; extra == "dev"
Requires-Dist: setuptools>=63.2 ; extra == "dev"
Requires-Dist: pylint>=2.15.9 ; extra == "dev"
Requires-Dist: rich>=12.6.0 ; extra == "richdebug"
Project-URL: Home, https://github.com/Mrfiregem/shell-piper
Project-URL: Issues, https://github.com/Mrfiregem/shell-piper/issues
Provides-Extra: dev
Provides-Extra: richdebug
